aws_ref.py
aws_ref-1.0.dist-info/METADATA
aws_ref-1.0.dist-info/WHEEL
aws_ref-1.0.dist-info/entry_points.txt
aws_ref-1.0.dist-info/top_level.txt
aws_ref-1.0.dist-info/RECORD
