Metadata-Version: 2.1
Name: aws-ref
Version: 1.0
Summary: A CLI tool to explore AWS IAM actions and their condition key/Resource ARN format support
Author: Chowdhury Faizal
Project-URL: Source, https://github.com/yourusername/aws-iam-explorer
Keywords: aws iam cloudformation policy condition-keys tags arn
Classifier: Programming Language :: Python :: 3
Classifier: Programming Language :: Python :: 3.7
Classifier: Programming Language :: Python :: 3.8
Classifier: Programming Language :: Python :: 3.9
Classifier: Programming Language :: Python :: 3.10
Classifier: Programming Language :: Python :: 3.11
Classifier: Operating System :: OS Independent
Requires-Python: >=3.7
